{
  "SWJTSP12020": {"item_name": "스웨트셔츠", "style_name": "레터링 스웨트 셔츠"},
  "SSMSLP32000": {"item_name": "팬츠", "style_name": "사계절 슬림 슬랙스"},
  "TWEBLP72070": {"item_name": "팬츠", "style_name": "벨티드 스트레이트 슬랙스"},
  "T1BOD052010": {"item_name": "원피스", "style_name": "미디 벨티드 원피스"},
  "SJKPOP52150": {"item_name": "원피스", "style_name": "셔츠형 롱 원피스"},
  "SSKPOP32020": {"item_name": "니트", "style_name": "라운드넥 슬리브 니트"},
  "SSKPOP32130": {"item_name": "니트", "style_name": "시스루 라운드넥 니트"},
  "GS4M1PO901": {"item_name": "니트", "style_name": "캡 슬리브 하프넥 풀오버 니트"},
  "BN3A1PO07": {"item_name": "니트", "style_name": "니트 풀오버"},
  "BM3A0BL06": {"item_name": "블라우스", "style_name": "베이직 블라우스"},
  "SSMSLP32060": {"item_name": "팬츠", "style_name": "슬림핏 슬랙스"},
  "BN3A0OP10": {"item_name": "원피스", "style_name": "브이넥 원피스"},
  "BN3A0BL09": {"item_name": "블라우스", "style_name": "프릴 블라우스"},
  "GS3A0OP211": {"item_name": "원피스", "style_name": "패턴 원피스"},
  "GS4A1PO361": {"item_name": "니트", "style_name": "하프넥 니트"},
  "TWWSTQ62070": {"item_name": "티셔츠", "style_name": "베이직 티셔츠"},
  "BN3A0OP15": {"item_name": "원피스", "style_name": "셔츠형 원피스"},
  "TSKCDQ52010": {"item_name": "가디건", "style_name": "라운드넥 가디건"},
  "TWWSLP72040": {"item_name": "팬츠", "style_name": "모던 히든 와이드 팬츠"},
  "TWWSLP72070": {"item_name": "팬츠", "style_name": "베이직 원턱 스트레이트 팬츠"},
  "SSKPOP31710": {"item_name": "니트", "style_name": "울 혼방 슬리브리스 니트"},
  "GS2A0SK111": {"item_name": "스커트", "style_name": "벨티드 백 슬릿 펜슬 스커트"},
  "GR3M0SL901": {"item_name": "팬츠", "style_name": "모던 슬림핏 부츠컷 팬츠"},
  "GS4A0OP371": {"item_name": "원피스", "style_name": "타이 레이어 재킷 H라인 원피스"},
  "GS4M0BL901": {"item_name": "블라우스", "style_name": "셔츠 배색 뷔스티에 블라우스"},
  "GS2M0JK901": {"item_name": "자켓", "style_name": "울 블렌드 크롭 트위드 재킷"},
  "GS4A3LT361": {"item_name": "자켓", "style_name": "오버핏 쓰리버튼 재킷"},
  "GS3M0BL931": {"item_name": "블라우스", "style_name": "레이어 패널 칼라 블라우스"},
  "GSRA0SL011": {"item_name": "팬츠", "style_name": "에센셜 레큘러핏 슬랙스 팬츠"},
  "CM3A0TC72": {"item_name": "코트", "style_name": "포켓 벨티드 트렌치 코트"},
  "CMAA0OP02": {"item_name": "원피스", "style_name": "크롭 재킷 셋업 원피스"},
  "CN2A0SL70": {"item_name": "팬츠", "style_name": "슬림핏 울 블렌드 팬츠슬랙스"},
  "BN2A0BL81": {"item_name": "블라우스", "style_name": "베이직 블라우스"},
  "BN3A0JK04": {"item_name": "자켓", "style_name": "노카라 트위드 재킷"},
  "BN3A0BL02": {"item_name": "블라우스", "style_name": "타이 넥 블라우스"},
  "SSKCDP31710": {"item_name": "가디건", "style_name": "울 혼방 브이넥 가디건"}
}
